ErrorHook/__init__.py
ErrorHook/clib.py
ErrorHook/hash.file
ErrorHook/update.py
ErrorHook-2.3.0.dist-info/LICENSE
ErrorHook-2.3.0.dist-info/METADATA
ErrorHook-2.3.0.dist-info/WHEEL
ErrorHook-2.3.0.dist-info/top_level.txt
ErrorHook-2.3.0.dist-info/RECORD
